input_validation/__init__.py
input_validation/main.py
input_validation/dist/index.html
input_validation/dist/assets/index-DcsT-qWp.css
input_validation/dist/assets/index-N7v-x3k6.js
input_validation_moveread-0.1.2.dist-info/METADATA
input_validation_moveread-0.1.2.dist-info/WHEEL
input_validation_moveread-0.1.2.dist-info/top_level.txt
input_validation_moveread-0.1.2.dist-info/RECORD
