Metadata-Version: 2.1
Name: input-validation-moveread
Version: 0.1.2
Summary: package_description
Author-email: Marcel Claramunt <marcel@moveread.com>
Project-URL: repo, https://github.com/moveread/REPO.git
Requires-Python: >=3.10
